anjin/__init__.py
anjin/__main__.py
anjin/changelog_registry.py
anjin/config.py
anjin/release_notes.py
anjin-0.1.1.dist-info/METADATA
anjin-0.1.1.dist-info/WHEEL
anjin-0.1.1.dist-info/entry_points.txt
anjin-0.1.1.dist-info/RECORD
