Metadata-Version: 2.3
Name: anjin
Version: 0.1.1
Summary: Add your description here
Author-email: Michael Smedes <smichaelmedes@gmail.com>
Requires-Python: >=3.8
Requires-Dist: changelogs>=0.15.0
Requires-Dist: httpx>=0.27.0
Requires-Dist: openai>=1.42.0
Requires-Dist: packaging>=24.1
Requires-Dist: pydantic-settings>=2.4.0
Requires-Dist: pydantic>=2.8.2
Requires-Dist: python-dotenv>=1.0.1
Requires-Dist: rich>=13.7.1
Requires-Dist: typer>=0.12.5
